collective.splitsitemap-1.1.1-py3.13-nspkg.pth
collective/splitsitemap/__init__.py
collective/splitsitemap/configure.zcml
collective/splitsitemap/interfaces.py
collective/splitsitemap/permissions.zcml
collective/splitsitemap/setuphandlers.py
collective/splitsitemap/testing.py
collective/splitsitemap/browser/__init__.py
collective/splitsitemap/browser/configure.zcml
collective/splitsitemap/browser/controlpanel.py
collective/splitsitemap/browser/sitemap.py
collective/splitsitemap/browser/sitemap.xml
collective/splitsitemap/browser/sitemap_index_template.xml
collective/splitsitemap/browser/overrides/.gitkeep
collective/splitsitemap/browser/static/.gitkeep
collective/splitsitemap/locales/README.rst
collective/splitsitemap/locales/__init__.py
collective/splitsitemap/locales/collective.splitsitemap.pot
collective/splitsitemap/locales/update.py
collective/splitsitemap/locales/update.sh
collective/splitsitemap/locales/en/LC_MESSAGES/collective.splitsitemap.po
collective/splitsitemap/profiles/default/browserlayer.xml
collective/splitsitemap/profiles/default/catalog.xml
collective/splitsitemap/profiles/default/controlpanel.xml
collective/splitsitemap/profiles/default/metadata.xml
collective/splitsitemap/profiles/default/registry.xml
collective/splitsitemap/profiles/default/rolemap.xml
collective/splitsitemap/profiles/uninstall/browserlayer.xml
collective/splitsitemap/scripts/__init__.py
collective/splitsitemap/scripts/generate_sitemaps.py
collective/splitsitemap/tests/__init__.py
collective/splitsitemap/tests/test_robot.py
collective/splitsitemap/tests/test_setup.py
collective/splitsitemap/tests/robot/test_example.robot
collective.splitsitemap-1.1.1.dist-info/LICENSE.GPL
collective.splitsitemap-1.1.1.dist-info/LICENSE.rst
collective.splitsitemap-1.1.1.dist-info/METADATA
collective.splitsitemap-1.1.1.dist-info/WHEEL
collective.splitsitemap-1.1.1.dist-info/entry_points.txt
collective.splitsitemap-1.1.1.dist-info/namespace_packages.txt
collective.splitsitemap-1.1.1.dist-info/top_level.txt
collective.splitsitemap-1.1.1.dist-info/RECORD
