Metadata-Version: 2.1
Name: collective.splitsitemap
Version: 1.1.1
Summary: An add-on for Plone
Home-page: https://github.com/collective/collective.splitsitemap
Author: Enfold Systems, Inc.
Author-email: info@enfoldsystems.com
License: GPL version 2
Project-URL: PyPI, https://pypi.python.org/pypi/collective.splitsitemap
Project-URL: Source, https://github.com/collective/collective.splitsitemap
Project-URL: Tracker, https://github.com/collective/collective.splitsitemap/issues
Keywords: Python Plone CMS
Classifier: Environment :: Web Environment
Classifier: Framework :: Plone
Classifier: Framework :: Plone :: Addon
Classifier: Framework :: Plone :: 4.3
Classifier: Programming Language :: Python
Classifier: Programming Language :: Python :: 2.7
Classifier: Programming Language :: Python :: 3
Classifier: Operating System :: OS Independent
Classifier: License :: OSI Approved :: GNU General Public License v2 (GPLv2)
License-File: LICENSE.GPL
License-File: LICENSE.rst
Requires-Dist: setuptools
Requires-Dist: six
Requires-Dist: z3c.jbot
Requires-Dist: Products.GenericSetup>=1.8.2
Requires-Dist: plone.schema
Provides-Extra: test
Requires-Dist: plone.app.testing; extra == "test"
Requires-Dist: plone.testing>=5.0.0; extra == "test"
Requires-Dist: plone.app.robotframework[debug]; extra == "test"
